pyloobins/__init__.py
pyloobins/cli.py
pyloobins/models.py
pyloobins/templates/loobin.md.j2
pyloobins/util.py
pyloobins-2.0.7.dist-info/METADATA
pyloobins-2.0.7.dist-info/WHEEL
pyloobins-2.0.7.dist-info/entry_points.txt
pyloobins-2.0.7.dist-info/licenses/LICENSE
pyloobins-2.0.7.dist-info/RECORD
