Metadata-Version: 2.4
Name: PyLOOBins
Version: 2.0.7
Summary: Python package for managing the LOOBins model and schema.
License: GPL-3.0-or-later
License-File: LICENSE
Keywords: cybersecurity,cli,lol
Author: infosecB
Author-email: brendan@infosecb.com
Requires-Python: >=3.8,<4.0
Classifier: License :: OSI Approved :: GNU General Public License v3 or later (GPLv3+)
Classifier: Programming Language :: Python :: 3
Classifier: Programming Language :: Python :: 3.8
Classifier: Programming Language :: Python :: 3.9
Classifier: Programming Language :: Python :: 3.10
Classifier: Programming Language :: Python :: 3.11
Classifier: Programming Language :: Python :: 3.12
Classifier: Programming Language :: Python :: 3.13
Classifier: Programming Language :: Python :: 3.14
Requires-Dist: click (>=8.1.3,<9.0.0)
Requires-Dist: jinja2 (>=3.1.2,<4.0.0)
Requires-Dist: polyfactory (>=2.18.0,<3.0.0)
Requires-Dist: pydantic (>=2,<3)
Requires-Dist: pyyaml (>=6.0,<7.0)
Requires-Dist: stix2 (>=3.0.1,<4.0.0)
Project-URL: Homepage, https://loobins.io/
Project-URL: Repository, https://github.com/infosecB/LOOBins
